{"label": "spam", "to_address": "the00@plg.uwaterloo.ca", "from_address": "Hagan Cooper <vigyanl@bar-plate.com>", "subject": "Have the best med$ at hand with u$!", "body": " Place in opposition the picture which Tacitus draws of Vitellius, fallen from empire, prolonging his ignominy from a wretched love of life, delivered over to the merciless rabble; tossed, buffeted, and kicked about; constrained, by their holding a poniard under his chin, to raise his head, and expose himself to every contumely. What abject infamy! What low humiliation! Yet even here, says the historian, he discovered some symptoms of a mind not wholly degenerate. To a tribune, who insulted him, he replied, I AM STILL YOUR EMPEROR."}