{"label": "ham", "to_address": "Erik Blankinship <jedierikb@gmail.com>", "from_address": "Marco Pesenti Gritti <mpg@redhat.com>", "subject": "Re: [sugar] Game key events", "body": " 63 (return) [ See the character of Antistius Labeo in Tacitus, (Annal. iii. 75,) and in an epistle of Ateius Capito, (Aul. Gellius, xiii. 12,) who accuses his rival of libertas nimia et vecors. Yet Horace would not have lashed a virtuous and respectable senator; and I must adopt the emendation of Bentley, who reads Labieno insanior, (Serm. I. iii. 82.) See Mascou, de Sectis, (c. i. p. 1\u201424.)]"}