{"label": "ham", "to_address": "speakup@braille.uwo.ca", "from_address": "Jude DaShiell <jdashiel@shellworld.net>", "subject": "procmail and clamav", "body": " With these words I was thinking that I had made an end of the discussion; but the end, in truth, proved to be only a beginning. For Glaucon, who is always the most pugnacious of men, was dissatisfied at Thrasymachus\u2019 retirement; he wanted to have the battle out. So he said to me: Socrates, do you wish really to persuade us, or only to seem to have persuaded us, that to be just is always better than to be unjust?"}