{"label": "ham", "to_address": "\"Speakup is a screen review system for Linux.\" <speakup@braille.uwo.ca>", "from_address": "\"Glenn Ervin\" <GlennErvin@cableone.net>", "subject": "Re: TTSynth Is Here At Last", "body": " 72 (return) [ Codex Theodos. l. vii. tit. xiii. leg. 16. The date of this law A.D. 406. May 18 satisfies me, as it had done Godefroy, (tom. ii. p. 387,) of the true year of the invasion of Radagaisus. Tillemont, Pagi, and Muratori, prefer the preceding year; but they are bound, by certain obligations of civility and respect, to St. Paulinus of Nola.]"}