{"label": "ham", "to_address": "samba-cvs@samba.org", "from_address": "vlendec@samba.org", "subject": "svn commit: samba r23183 - in branches: SAMBA_3_0/source\n\tSAMBA_3_0/source/include SAMBA_3_0/source/lib\n\tSAMBA_3_0/source/libsmb SAMBA_3_0/source/locking\n\tSAMBA_3_0/source/printing SAMBA_3_0/source/rpc_server\n\tSAMBA_3_0/source/smbd SAMBA_3_0/source/torture\n\tSAMBA_3_0/source/utils SAMBA_3_0_26/source\n\tSAMBA_3_0_26/source/include SAMBA_3_0_26/source/libsmb\n\tSAMBA_3_0_26/source/locking SAMBA_3_0_26/source/printing\n\tSAMBA_3_0_26/source/rpc_server SAMBA_3_0_26/source/smbd\n\tSAMBA_3_0_26/source/torture SAMBA_3_0_26/source/utils", "body": " 44 (return) [ Zosim. l. ii. p. 106. Chron. Alexandrin. vel Paschal. p. 284, Ducange, Const. l. i. c. 24. Even the last of those writers seems to confound the Forum of Constantine with the Augusteum, or court of the palace. I am not satisfied whether I have properly distinguished what belongs to the one and the other.]"}