{"label": "spam", "to_address": "ktwarwic@flax9.uwaterloo.ca", "from_address": "\"Capps, Cristina\" <CristinazCapps@comprehensive1.com>", "subject": "Cash to your Door  ", "body": " Nan Chung, our chief, had heard the royal call To go where inroad by Heen-yuns was made, And 'cross the frontier build a barrier wall. Numerous his chariots, splendidly arrayed! The standards--this where dragons were displayed, And that where snakes round tortoises were coiled-- Terrific flew. \"Northward our host,\" he said, \"Heaven's son sends forth to tame the Heen-yun wild.\" Soon by this awful chief would all their tribes be foiled."}