{"label": "ham", "to_address": "beginners@perl.org, perl-beginners@moderators.isc.org", "from_address": "\"nobull67@gmail.com\" <nobull67@gmail.com>", "subject": "Re: Passing arguments to subroutine", "body": " 18 (return) [ Cqamalh edra, which Cinnamus translates into Latin by the word Sellion. Ducange works very hard to save his king and country from such ignominy, (sur Joinville, dissertat. xxvii. p. 317\u2014320.) Louis afterwards insisted on a meeting in mari ex \u00e6quo, not ex equo, according to the laughable readings of some MSS.]"}