{"label": "spam", "to_address": "cruiseca@flax9.uwaterloo.ca", "from_address": "\"Be in the Studio Audience\" <return@bandanestring.com>", "subject": "See Oprah Live - Get an All Expenses Paid Trip", "body": " Achaeus, a wise and prudent prince, fell into a fatal snare, which cost him his crown and life, after having used every reasonable precaution to guard himself against it. On that account, says the historian, he is a just object of regard and compassion: his betrayers alone of hatred and contempt [Footnote: Polybius, lib. iii. cap. 2]."}