{"label": "spam", "to_address": "gnitpick@flax9.uwaterloo.ca", "from_address": "\"Herminia Ledbetter\" <cajmpbmug@mpb.in>", "subject": "Hey - Don't get ripped off", "body": " 8. After having done this they produce their young. There is nothing to prevent there being grubs, and honey, and drones in the same comb. As long as the king bee is alive, they say that the drones are produced in a separate place; but when he is dead they are produced by the bees in their own cells, and such drones are more passionate: for this cause they are called stingers, not that they have any sting, but that they would sting, if they had the power to do so. The drone cells are larger. Sometimes the drone cells are placed by themselves, but are generally combined with those of bees, for which reason they cut them off."}