{"label": "spam", "to_address": "<jegdcorxchqgnitpick@flax9.uwaterloo.ca>", "from_address": "\"Leila Craig\" <leoda990@hotmail.com>", "subject": "Don't waste your money", "body": " III. There have been many objections drawn from the mathematics against the indivisibility of the parts of extension: though at first sight that science seems rather favourable to the present doctrine; and if it be contrary in its DEMONSTRATIONS, it is perfectly conformable in its definitions. My present business then must be to defend the definitions, and refute the demonstrations."}