{"label": "ham", "to_address": "Chas Owens <chas.owens@gmail.com>", "from_address": "Tom Allison <tom@tacocat.net>", "subject": "Re: forking problem with dbd::mysql", "body": " 95 (return) [ Si nullae a republica vires, nulla praesidia; si nullae, quantum rumor est, Anthemii principis opes; statuit, te auctore, nobilitas, seu patriaca dimittere seu capillos, (Sidon. l. ii. epist. 1, p. 33.) The last words Sirmond, (Not. p. 25) may likewise denote the clerical tonsure, which was indeed the choice of Sidonius himself.]"}