{"label": "spam", "to_address": "<the00@plg.uwaterloo.ca>", "from_address": "\"Donald Taylor\" <higherpraisechurch.com@park.funnel.revenuedirect.com.akadns.net>", "subject": "Corel Draw", "body": " 15. The wasps which are called ichneumons, which are smaller than the others, kill the phalangia, and carry them to a wall, or some other place with a hole in it; and when they have covered them over with mud, they oviposit there, and the ichneumon wasps are produced from them. Many of the coleoptera, and other small and anonymous creatures make little holes in tombs or walls, and there deposit their worms."}