{"label": "ham", "to_address": "\"Speakup is a screen review system for Linux.\" <speakup@braille.uwo.ca>", "from_address": "Igor Gueths <igueths@lava-net.com>", "subject": "Re: dectalk express with Linux-2.6.21.5", "body": " 29 (return) [ Bulgari, Boulgres, Bougres, a national appellation, has been applied by the French as a term of reproach to usurers and unnatural sinners. The Paterini, or Patelini, has been made to signify a smooth and flattering hypocrite, such as l\u2019Avocat Patelin of that original and pleasant farce, (Ducange, Gloss. Latinitat. Medii et Infimi Aevi.) The Manichaeans were likewise named Cathari or the pure, by corruption. Gazari, &c.]"}