{"label": "spam", "to_address": "\"Subscriber\" <cruiseca@flax9.uwaterloo.ca>", "from_address": "\"Land Deal\" <qg_di9zmi@facespry.com>", "subject": "Pre-development pricing in Costa Rica ", "body": " 7. And again in fishing, the fishermen are careful to avoid making a noise with their oars or net when they perceive many fish collected in one place; they make a signal, and let down their nets in such a place that no sound of the oar or the motion of the waters should reach the place where the fish are collected, and the sailors are commanded to row in the greatest silence until they have enclosed them."}